docopt2ragel/__init__.py
docopt2ragel/__main__.py
docopt2ragel/docopt2ragel.py
docopt2ragel/template.rl
docopt2ragel-0.1.4.dist-info/DESCRIPTION.rst
docopt2ragel-0.1.4.dist-info/METADATA
docopt2ragel-0.1.4.dist-info/RECORD
docopt2ragel-0.1.4.dist-info/WHEEL
docopt2ragel-0.1.4.dist-info/entry_points.txt
docopt2ragel-0.1.4.dist-info/metadata.json
docopt2ragel-0.1.4.dist-info/top_level.txt
