Metadata-Version: 2.0
Name: docopt2ragel
Version: 0.1.4
Summary: Convert your docopt usage text into a Ragel FSM
Home-page: https://github.com/willemt/docopt2ragel
Author: willemt
Author-email: himself@willemthiart.com
License: BSD
Keywords: development
Platform: UNKNOWN
Classifier: Development Status :: 3 - Alpha
Classifier: Intended Audience :: Developers
Classifier: Topic :: System :: Logging
Classifier: License :: OSI Approved :: BSD License
Classifier: Programming Language :: Python :: 2.6
Classifier: Programming Language :: Python :: 2.7
Requires-Dist: docopt
